dabom/__init__.py
dabom/api.py
dabom/exceptions.py
dabom_python-0.1.0.dist-info/LICENSE
dabom_python-0.1.0.dist-info/METADATA
dabom_python-0.1.0.dist-info/WHEEL
dabom_python-0.1.0.dist-info/top_level.txt
dabom_python-0.1.0.dist-info/RECORD
